sharktanklang/__init__.py
sharktanklang/cli.py
sharktanklang/interpreter.py
sharktanklang-0.1.0.dist-info/METADATA
sharktanklang-0.1.0.dist-info/WHEEL
sharktanklang-0.1.0.dist-info/entry_points.txt
sharktanklang-0.1.0.dist-info/top_level.txt
sharktanklang-0.1.0.dist-info/RECORD
