Metadata-Version: 2.4
Name: sharktanklang
Version: 0.1.0
Summary: Shark Tank India themed programming language
Author: Nikhil Raj
License: MIT
Project-URL: Homepage, https://github.com/nikhiilraj/SharktankLang
Requires-Python: >=3.8
